abba/__init__.py
abba/cert.py
abba/main.py
abba/__pycache__/cert.cpython-38.pyc
abba/models/__init__.py
abba/models/mo.py
abba/modules/__init__.py
abba/modules/abc.py
abba_models-0.0.4.dist-info/DESCRIPTION.rst
abba_models-0.0.4.dist-info/METADATA
abba_models-0.0.4.dist-info/RECORD
abba_models-0.0.4.dist-info/WHEEL
abba_models-0.0.4.dist-info/metadata.json
abba_models-0.0.4.dist-info/top_level.txt
